axelrod/__init__.py
axelrod/_strategy_utils.py
axelrod/action.py
axelrod/classifier.py
axelrod/compute_finite_state_machine_memory.py
axelrod/deterministic_cache.py
axelrod/ecosystem.py
axelrod/eigen.py
axelrod/evolvable_player.py
axelrod/fingerprint.py
axelrod/game.py
axelrod/graph.py
axelrod/history.py
axelrod/interaction_utils.py
axelrod/load_data_.py
axelrod/makes_use_of.py
axelrod/match.py
axelrod/match_generator.py
axelrod/mock_player.py
axelrod/moran.py
axelrod/player.py
axelrod/plot.py
axelrod/random_.py
axelrod/result_set.py
axelrod/strategy_transformers.py
axelrod/tournament.py
axelrod/version.py
axelrod/data/all_classifiers.yml
axelrod/data/ann_weights.csv
axelrod/data/model_attention.pth
axelrod/data/pso_gambler.csv
axelrod/strategies/__init__.py
axelrod/strategies/_filters.py
axelrod/strategies/_strategies.py
axelrod/strategies/adaptive.py
axelrod/strategies/adaptor.py
axelrod/strategies/alternator.py
axelrod/strategies/ann.py
axelrod/strategies/apavlov.py
axelrod/strategies/appeaser.py
axelrod/strategies/attention.py
axelrod/strategies/averagecopier.py
axelrod/strategies/axelrod_first.py
axelrod/strategies/axelrod_second.py
axelrod/strategies/backstabber.py
axelrod/strategies/better_and_better.py
axelrod/strategies/bush_mosteller.py
axelrod/strategies/calculator.py
axelrod/strategies/cooperator.py
axelrod/strategies/cycler.py
axelrod/strategies/darwin.py
axelrod/strategies/dbs.py
axelrod/strategies/defector.py
axelrod/strategies/doubler.py
axelrod/strategies/finite_state_machines.py
axelrod/strategies/forgiver.py
axelrod/strategies/frequency_analyzer.py
axelrod/strategies/gambler.py
axelrod/strategies/gobymajority.py
axelrod/strategies/gradualkiller.py
axelrod/strategies/grudger.py
axelrod/strategies/grumpy.py
axelrod/strategies/handshake.py
axelrod/strategies/hmm.py
axelrod/strategies/hunter.py
axelrod/strategies/inverse.py
axelrod/strategies/lookerup.py
axelrod/strategies/mathematicalconstants.py
axelrod/strategies/memoryone.py
axelrod-4.14.0.dist-info/METADATA
axelrod-4.14.0.dist-info/WHEEL
axelrod-4.14.0.dist-info/licenses/LICENSE.txt
axelrod-4.14.0.dist-info/RECORD
