Metadata-Version: 2.4
Name: Axelrod
Version: 4.14.0
Summary: Reproduce the Axelrod iterated prisoners dilemma tournament
Project-URL: Homepage, http://axelrod.readthedocs.org/
Author: Owen Campbell, Karol Langner, Marc Harper
Author-email: Vince Knight <axelrod-python@googlegroups.com>
License-File: LICENSE.txt
Classifier: License :: OSI Approved :: MIT License
Classifier: Programming Language :: Python :: 3 :: Only
Classifier: Programming Language :: Python :: 3.11
Classifier: Programming Language :: Python :: 3.12
Requires-Python: >=3.6
Requires-Dist: cloudpickle>=0.2.2
Requires-Dist: dask[dataframe]>=2.9.2
Requires-Dist: fsspec>=0.6.0
Requires-Dist: matplotlib>=3.0.3
Requires-Dist: numpy>=1.26.4
Requires-Dist: pandas>=1.0.0
Requires-Dist: pyyaml>=5.1
Requires-Dist: scipy>=1.3.3
Requires-Dist: toolz>=0.8.2
Requires-Dist: torch>=2.6.0
Requires-Dist: tqdm>=4.39.0
Provides-Extra: development
Requires-Dist: hypothesis==5.19.3; extra == 'development'
Provides-Extra: human
Requires-Dist: prompt-toolkit>=3.0; extra == 'human'
